Workbook

Sheet Обложка
B2: Финансовая модель: запуск нового продукта
B3: Инвестиционное решение о запуске новой линейки промышленных чиллеров
B5: О модели
B6: Иллюстративный кейс для портфолио: оценка запуска нового продукта на существующем производстве. Все цифры — обобщённые допущения, НЕ реальные показатели конкретной компании.
B8: Структура и содержание
B9: Итоги — Главные цифры: NPV, IRR, срок окупаемости, 2 графика — для быстрого просмотра
B10: Допущения — Все вводные данные с источником/обоснованием для каждой группы
B11: Модель — Помесячный расчёт (год 1–2) и погодовой (год 3–5): выручка > затраты > EBIT > FCF
B12: Сценарии — Пессимистичный / База / Оптимистичный — сравнение по годам
B13: Чувствительность — Как меняется NPV при изменении цены и ставки дисконтирования
B15: Легенда цвета ячеек
B16: Синий текст — вводные данные — можно менять
... B19: Жёлтая заливка — ключевое допущение, к которому стоит вернуться в первую очередь

Sheet Итоги
B2: Итоги: запуск новой линейки промышленных чиллеров
B4: NPV, IRR, срок окупаемости
B6: NPV на явном горизонте (5 лет), руб. | C6: =Модель!AC31 -> 8881137.9
B7: + Остаточная стоимость (2 доп. года по уровню Года 5, без роста — консервативно) | C7: =Модель!AC27/(1+Допущения!C7)^6+Модель!AC27/(1+Допущения!C7)^7 -> 43463618
B8: ИТОГОВЫЙ NPV, руб. | C8: =C6+C7 -> 52344755
B10: IRR (перебор ставок по факт. датам ден. потока) | C10: =Модель!$B$40 -> 0.23991898
B11: Ставка дисконтирования (для сравнения) | C11: =Допущения!C7 -> 0.2
B13: Срок окупаемости (недисконтированный), лет | C13: =(INDEX(Модель!B6:AC6,SUMPRODUCT(--(Модель!B30:AC30<0))+1-1)+(0-INDEX(Модель!B30:AC30,SUMPRODUCT(--(Модель!B30:AC30<0))+1-1))/(INDEX(Модель!B30:AC30,SUMPRODUCT(--(Модель!B30:AC30<0))+1)-INDEX(Модель!B30:AC30,SUMPRODUCT(--(Модель!B30:AC30<0))+1-1))*(INDEX(Модель!B6:AC6,SUMPRODUCT(--(Модель!B30:AC30<0))+1)-INDEX(Модель!B6:AC6,SUMPRODUCT(--(Модель!B30:AC30<0))+1-1))-Модель!B6)/365.25 -> 3.673679 | D13: лет
B14: Линейная интерполяция между последним отрицательным и первым положительным накопленным FCF по фактическим датам (не по номеру периода — периоды разной длины)
B16: Графики

Sheet Допущения
B1: Допущения
B3: Параметр | C3: Значение | D3: Ед. изм. | E3: Источник / обоснование
B4: 1. Ставка дисконтирования
B5: Ключевая ставка ЦБ РФ, год. | C5: 0.14 | D5: % | E5: Решение Совета директоров Банка России от 24.07.2026 — снижение до 14,00% годовых
B6: Премия за риск нового продукта | C6: 0.06 | D6: % | E6: Экспертная оценка. Рыночная премия за риск в РФ обычно 6–9 п.п. сверх безрисковой ставки (метод кумулятивного построения); взят нижний край диапазона, т.к. продукт запускается на действующем производстве и сбыте, а не «с нуля»
B7: Ставка дисконтирования, годовая | C7: =C5+C6 -> 0.2 | D7: % | E7: Ключевая ставка + премия за риск
B8: Ставка дисконтирования, месячная | C8: =(1+C7)^(1/12)-1 -> 0.01530947 | D8: % | E8: (1+годовая)^(1/12) − 1, корректная конвертация через сложный процент, а не деление на 12
B10: 2. Рынок и продукт
B11: Средняя цена за единицу (Год 1–4) | C11: 3000000 | D11: ₽/шт | E11: Порядок величины по открытым прайс-листам промышленных чиллеров средней/повышенной мощности (среднероссийская мощность чиллера >300 кВт)
B12: Темп роста рынка | C12: 0.05 | D12: %/год | E12: Ориентир по открытым обзорам рынка промышленного холодильного оборудования РФ (рост объёма рынка на фоне импортозамещения после ухода ряда зарубежных брендов)
B13: Прирост цены в Год 5 (реализация рыночного роста, когда объём упирается в мощность) | C13: =C12 -> 0.05 | D13: % | E13: Равно темпу роста рынка: после выхода на потолок мощности рост показывается в цене, а не в объёме
B15: 3. Мощность и CAPEX
B16: Начальный CAPEX (Мес. 0) | C16: 40000000 | D16: ₽ | E16: Оценка включает: адаптация производственной линии, оснастка, сертификация новой модели.
B17: Начальная мощность | C17: 6 | D17: шт/мес | E17: Допущение согласно масштабу CAPEX выше
B18: CAPEX расширения (начало Года 3) | C18: 30000000 | D18: ₽ | E18: Оценка расширения мощности под растущий спрос
B19: Мощность после расширения | C19: 10 | D19: шт/мес
B20: Срок полезного использования оборудования | C20: 7 | D20: лет | E20: Промышленное технологическое оборудование обычно относится к 4–5 амортизационной группе (СПИ 5–10 лет по Классификации ОС РФ); взята середина диапазона
B22: 4. Затраты
B23: Переменные затраты на единицу | C23: 1900000 | D23: ₽/шт | E23: ≈63% от цены > маржинальность (выручка−переем.затраты)/выручка ≈ 36,7% — ориентир на валовую маржу производственного бизнеса до вычета пост. затрат
B24: Постоянные затраты (произв.+админ.), Год 1–2 | C24: 3000000 | D24: ₽/мес | E24: Оценка для начальной мощности
B25: Постоянные затраты (произв.+админ.), Год 3+ | C25: 3800000 | D25: ₽/мес | E25: Рост пропорционально расширению мощности
B26: Маркетинг и продажи, Год 1–2 | C26: 1000000 | D26: ₽/мес | E26: Ориентир: 2 менеджера по работе с B2B-клиентами (полная стоимость) + участие в отраслевых выставках/каталоги
B27: Маркетинг и продажи, Год 3+ | C27: 1300000 | D27: ₽/мес | E27: Расширение команды продаж пропорционально мощности
B29: 5. Продажи и оборотный капитал
B30: Средний цикл сделки B2B | C30: 5 | D30: мес | E30: Для промышленного оборудования — от нескольких месяцев до года и более (как обоснование медленного разгона продаж в допущении по объёму в Модели)
B31: Длина периода | C31: 30 | D31: дней
B32: Запасы: средний срок оборачиваемости | C32: 45 | D32: дней | E32: Поставил экспертно 1,5 месяца - зависит от производства
B33: Отсрочка платежа (DSO) | C33: 45 | D33: дней | E33: Стандартная практика для B2B-продаж капитального оборудования; конвертация: 45/30 для месячных периодов, 45/360 для годовых (день/360 конвенция)
B34: Отсрочка поставщиков (DPO) | C34: 45 | D34: дней | E34: Зависит от условий, на которых работаем с поставщиками
B36: 6. Налоги
B37: Ставка налога на прибыль | C37: 0.2 | D37: % | E37: Ставка налога на прибыль организаций в РФ
B39: 7. Переключатель сценария (используется на листе «Сценарии»)
B40: Активный сценарий | C40: База | E40: Выпадающий список — переключает набор допущений на вкладке «Сценарии»
B42: Длина периода (год), дней | C42: 360 | D42: дней | E42: Используется для расчета NWC, но для ГОДОВЫХ колонок (Год 3-5)

Sheet Модель
A1: Модель: помесячно (Год 1–2) и по годам (Год 3–5)
A5: Период | B5: Мес. 0 | C5: Мес. 1 | D5: Мес. 2 | E5: Мес. 3 | F5: Мес. 4 | G5: Мес. 5 | H5: Мес. 6 | I5: Мес. 7 | J5: Мес. 8 | K5: Мес. 9 | L5: Мес. 10 | M5: Мес. 11 | N5: Мес. 12 | O5: Мес. 13 | P5: Мес. 14 | Q5: Мес. 15 | R5: Мес. 16 | S5: Мес. 17 | T5: Мес. 18 | U5: Мес. 19 | V5: Мес. 20 | W5: Мес. 21 | X5: Мес. 22 | Y5: Мес. 23 | Z5: Мес. 24 | AA5: Год 3 | AB5: Год 4 | AC5: Год 5
A6: Дата периода (для XIRR/IRR) | B6: =DATE(2026,9,1) -> 46266 | C6: =EDATE($B$6,1) -> 46296 | D6: =EDATE($B$6,2) -> 46327 | E6: =EDATE($B$6,3) -> 46357 | F6: =EDATE($B$6,4) -> 46388 | G6: =EDATE($B$6,5) -> 46419 | H6: =EDATE($B$6,6) -> 46447 | I6: =EDATE($B$6,7) -> 46478 | J6: =EDATE($B$6,8) -> 46508 | K6: =EDATE($B$6,9) -> 46539 | L6: =EDATE($B$6,10) -> 46569 | M6: =EDATE($B$6,11) -> 46600 | N6: =EDATE($B$6,12) -> 46631 | O6: =EDATE($B$6,13) -> 46661 | P6: =EDATE($B$6,14) -> 46692 | Q6: =EDATE($B$6,15) -> 46722 | R6: =EDATE($B$6,16) -> 46753 | S6: =EDATE($B$6,17) -> 46784 | T6: =EDATE($B$6,18) -> 46813 | U6: =EDATE($B$6,19) -> 46844 | V6: =EDATE($B$6,20) -> 46874 | W6: =EDATE($B$6,21) -> 46905 | X6: =EDATE($B$6,22) -> 46935 | Y6: =EDATE($B$6,23) -> 46966 | Z6: =EDATE($B$6,24) -> 46997 | AA6: =EDATE($B$6,36) -> 47362 | AB6: =EDATE($B$6,48) -> 47727 | AC6: =EDATE($B$6,60) -> 48092
A7: Мощность, шт./период | B7: 0 | C7: =Допущения!C17 -> 6 | D7: =Допущения!C17 -> 6 | E7: =Допущения!C17 -> 6 | F7: =Допущения!C17 -> 6 | G7: =Допущения!C17 -> 6 | H7: =Допущения!C17 -> 6 | I7: =Допущения!C17 -> 6 | J7: =Допущения!C17 -> 6 | K7: =Допущения!C17 -> 6 | L7: =Допущения!C17 -> 6 | M7: =Допущения!C17 -> 6 | N7: =Допущения!C17 -> 6 | O7: =Допущения!C17 -> 6 | P7: =Допущения!C17 -> 6 | Q7: =Допущения!C17 -> 6 | R7: =Допущения!C17 -> 6 | S7: =Допущения!C17 -> 6 | T7: =Допущения!C17 -> 6 | U7: =Допущения!C17 -> 6 | V7: =Допущения!C17 -> 6 | W7: =Допущения!C17 -> 6 | X7: =Допущения!C17 -> 6 | Y7: =Допущения!C17 -> 6 | Z7: =Допущения!C17 -> 6 | AA7: =Допущения!C19*12 -> 120 | AB7: =Допущения!C19*12 -> 120 | AC7: =Допущения!C19*12 -> 120
A8: Объём продаж, шт. | B8: 0 | C8: 0 | D8: 1 | E8: 1 | F8: 2 | G8: 2 | H8: 3 | I8: 3 | J8: 4 | K8: 4 | L8: 5 | M8: 5 | N8: 6 | O8: 6 | P8: 6 | Q8: 6 | R8: 6 | S8: 6 | T8: 6 | U8: 6 | V8: 6 | W8: 6 | X8: 6 | Y8: 6 | Z8: 6 | AA8: 120 | AB8: 120 | AC8: 120
A9: Цена за единицу, руб. | C9: =Допущения!C11 -> 3000000 | D9: =Допущения!C11 -> 3000000 | E9: =Допущения!C11 -> 3000000 | F9: =Допущения!C11 -> 3000000 | G9: =Допущения!C11 -> 3000000 | H9: =Допущения!C11 -> 3000000 | I9: =Допущения!C11 -> 3000000 | J9: =Допущения!C11 -> 3000000 | K9: =Допущения!C11 -> 3000000 | L9: =Допущения!C11 -> 3000000 | M9: =Допущения!C11 -> 3000000 | N9: =Допущения!C11 -> 3000000 | O9: =Допущения!C11 -> 3000000 | P9: =Допущения!C11 -> 3000000 | Q9: =Допущения!C11 -> 3000000 | R9: =Допущения!C11 -> 3000000 | S9: =Допущения!C11 -> 3000000 | T9: =Допущения!C11 -> 3000000 | U9: =Допущения!C11 -> 3000000 | V9: =Допущения!C11 -> 3000000 | W9: =Допущения!C11 -> 3000000 | X9: =Допущения!C11 -> 3000000 | Y9: =Допущения!C11 -> 3000000 | Z9: =Допущения!C11 -> 3000000 | AA9: =Допущения!C11 -> 3000000 | AB9: =Допущения!C11 -> 3000000 | AC9: =Допущения!C11*(1+Допущения!C13) -> 3150000
A10: Выручка, руб. | B10: =B8*B9 -> 0 | C10: =C8*C9 -> 0 | D10: =D8*D9 -> 3000000 | E10: =E8*E9 -> 3000000 | F10: =F8*F9 -> 6000000 | G10: =G8*G9 -> 6000000 | H10: =H8*H9 -> 9000000 | I10: =I8*I9 -> 9000000 | ... AC10: =AC8*AC9 -> 378000000
A11: Переменные затраты на ед., руб. | C11: =Допущения!C23 -> 1900000 | D11: =Допущения!C23 -> 1900000 | E11: =Допущения!C23 -> 1900000 | F11: =Допущения!C23 -> 1900000 | G11: =Допущения!C23 -> 1900000 | H11: =Допущения!C23 -> 1900000 | I11: =Допущения!C23 -> 1900000 | J11: =Допущения!C23 -> 1900000 | K11: =Допущения!C23 -> 1900000 | L11: =Допущения!C23 -> 1900000 | M11: =Допущения!C23 -> 1900000 | N11: =Допущения!C23 -> 1900000 | O11: =Допущения!C23 -> 1900000 | P11: =Допущения!C23 -> 1900000 | Q11: =Допущения!C23 -> 1900000 | R11: =Допущения!C23 -> 1900000 | S11: =Допущения!C23 -> 1900000 | T11: =Допущения!C23 -> 1900000 | U11: =Допущения!C23 -> 1900000 | V11: =Допущения!C23 -> 1900000 | W11: =Допущения!C23 -> 1900000 | X11: =Допущения!C23 -> 1900000 | Y11: =Допущения!C23 -> 1900000 | Z11: =Допущения!C23 -> 1900000 | AA11: =Допущения!C23 -> 1900000 | AB11: =Допущения!C23 -> 1900000 | AC11: =Допущения!C23 -> 1900000
A12: Переменные затраты, руб. | B12: =B8*B11 -> 0 | C12: =C8*C11 -> 0 | D12: =D8*D11 -> 1900000 | E12: =E8*E11 -> 1900000 | F12: =F8*F11 -> 3800000 | G12: =G8*G11 -> 3800000 | H12: =H8*H11 -> 5700000 | I12: =I8*I11 -> 5700000 | ... AC12: =AC8*AC11 -> 228000000
A13: Маржинальная прибыль, руб. | B13: =B10-B12 -> 0 | C13: =C10-C12 -> 0 | D13: =D10-D12 -> 1100000 | E13: =E10-E12 -> 1100000 | F13: =F10-F12 -> 2200000 | G13: =G10-G12 -> 2200000 | H13: =H10-H12 -> 3300000 | I13: =I10-I12 -> 3300000 | ... AC13: =AC10-AC12 -> 150000000
A14: Постоянные затраты (произв.+админ.), руб. | B14: 0 | C14: =Допущения!C24 -> 3000000 | D14: =Допущения!C24 -> 3000000 | E14: =Допущения!C24 -> 3000000 | F14: =Допущения!C24 -> 3000000 | G14: =Допущения!C24 -> 3000000 | H14: =Допущения!C24 -> 3000000 | I14: =Допущения!C24 -> 3000000 | J14: =Допущения!C24 -> 3000000 | K14: =Допущения!C24 -> 3000000 | L14: =Допущения!C24 -> 3000000 | M14: =Допущения!C24 -> 3000000 | N14: =Допущения!C24 -> 3000000 | O14: =Допущения!C24 -> 3000000 | P14: =Допущения!C24 -> 3000000 | Q14: =Допущения!C24 -> 3000000 | R14: =Допущения!C24 -> 3000000 | S14: =Допущения!C24 -> 3000000 | T14: =Допущения!C24 -> 3000000 | U14: =Допущения!C24 -> 3000000 | V14: =Допущения!C24 -> 3000000 | W14: =Допущения!C24 -> 3000000 | X14: =Допущения!C24 -> 3000000 | Y14: =Допущения!C24 -> 3000000 | Z14: =Допущения!C24 -> 3000000 | AA14: =Допущения!C25*12 -> 45600000 | AB14: =Допущения!C25*12 -> 45600000 | AC14: =Допущения!C25*12 -> 45600000
A15: Маркетинг и продажи, руб. | B15: 0 | C15: =Допущения!C26 -> 1000000 | D15: =Допущения!C26 -> 1000000 | E15: =Допущения!C26 -> 1000000 | F15: =Допущения!C26 -> 1000000 | G15: =Допущения!C26 -> 1000000 | H15: =Допущения!C26 -> 1000000 | I15: =Допущения!C26 -> 1000000 | J15: =Допущения!C26 -> 1000000 | K15: =Допущения!C26 -> 1000000 | L15: =Допущения!C26 -> 1000000 | M15: =Допущения!C26 -> 1000000 | N15: =Допущения!C26 -> 1000000 | O15: =Допущения!C26 -> 1000000 | P15: =Допущения!C26 -> 1000000 | Q15: =Допущения!C26 -> 1000000 | R15: =Допущения!C26 -> 1000000 | S15: =Допущения!C26 -> 1000000 | T15: =Допущения!C26 -> 1000000 | U15: =Допущения!C26 -> 1000000 | V15: =Допущения!C26 -> 1000000 | W15: =Допущения!C26 -> 1000000 | X15: =Допущения!C26 -> 1000000 | Y15: =Допущения!C26 -> 1000000 | Z15: =Допущения!C26 -> 1000000 | AA15: =Допущения!C27*12 -> 15600000 | AB15: =Допущения!C27*12 -> 15600000 | AC15: =Допущения!C27*12 -> 15600000
A16: Амортизация, руб. | B16: 0 | C16: =Допущения!C16/Допущения!C20/12 -> 476190.48 | D16: =Допущения!C16/Допущения!C20/12 -> 476190.48 | E16: =Допущения!C16/Допущения!C20/12 -> 476190.48 | F16: =Допущения!C16/Допущения!C20/12 -> 476190.48 | G16: =Допущения!C16/Допущения!C20/12 -> 476190.48 | H16: =Допущения!C16/Допущения!C20/12 -> 476190.48 | I16: =Допущения!C16/Допущения!C20/12 -> 476190.48 | J16: =Допущения!C16/Допущения!C20/12 -> 476190.48 | K16: =Допущения!C16/Допущения!C20/12 -> 476190.48 | L16: =Допущения!C16/Допущения!C20/12 -> 476190.48 | M16: =Допущения!C16/Допущения!C20/12 -> 476190.48 | N16: =Допущения!C16/Допущения!C20/12 -> 476190.48 | O16: =Допущения!C16/Допущения!C20/12 -> 476190.48 | P16: =Допущения!C16/Допущения!C20/12 -> 476190.48 | Q16: =Допущения!C16/Допущения!C20/12 -> 476190.48 | R16: =Допущения!C16/Допущения!C20/12 -> 476190.48 | S16: =Допущения!C16/Допущения!C20/12 -> 476190.48 | T16: =Допущения!C16/Допущения!C20/12 -> 476190.48 | U16: =Допущения!C16/Допущения!C20/12 -> 476190.48 | V16: =Допущения!C16/Допущения!C20/12 -> 476190.48 | W16: =Допущения!C16/Допущения!C20/12 -> 476190.48 | X16: =Допущения!C16/Допущения!C20/12 -> 476190.48 | Y16: =Допущения!C16/Допущения!C20/12 -> 476190.48 | Z16: =Допущения!C16/Допущения!C20/12 -> 476190.48 | AA16: =Допущения!C16/Допущения!C20+Допущения!C18/Допущения!C20 -> 10000000 | AB16: =Допущения!C16/Допущения!C20+Допущения!C18/Допущения!C20 -> 10000000 | AC16: =Допущения!C16/Допущения!C20+Допущения!C18/Допущения!C20 -> 10000000
A17: EBIT, руб. | B17: =B13-B14-B15-B16 -> 0 | C17: =C13-C14-C15-C16 -> -4476190.5 | D17: =D13-D14-D15-D16 -> -3376190.5 | E17: =E13-E14-E15-E16 -> -3376190.5 | F17: =F13-F14-F15-F16 -> -2276190.5 | G17: =G13-G14-G15-G16 -> -2276190.5 | H17: =H13-H14-H15-H16 -> -1176190.5 | I17: =I13-I14-I15-I16 -> -1176190.5 | ... AC17: =AC13-AC14-AC15-AC16 -> 78800000
A18: Налог на прибыль, руб. | B18: =B17*Допущения!C37 -> 0 | C18: =IF(C17 > 0, C17*Допущения!$C$37, 0) -> 0 | D18: =IF(D17 > 0, D17*Допущения!$C$37, 0) -> 0 | E18: =IF(E17 > 0, E17*Допущения!$C$37, 0) -> 0 | F18: =IF(F17 > 0, F17*Допущения!$C$37, 0) -> 0 | G18: =IF(G17 > 0, G17*Допущения!$C$37, 0) -> 0 | H18: =IF(H17 > 0, H17*Допущения!$C$37, 0) -> 0 | I18: =IF(I17 > 0, I17*Допущения!$C$37, 0) -> 0 | J18: =IF(J17 > 0, J17*Допущения!$C$37, 0) -> 0 | ... AC18: =IF(AC17 > 0, AC17*Допущения!$C$37, 0) -> 15760000
A19: Чистая прибыль, руб. | B19: =B17-B18 -> 0 | C19: =C17-C18 -> -4476190.5 | D19: =D17-D18 -> -3376190.5 | E19: =E17-E18 -> -3376190.5 | F19: =F17-F18 -> -2276190.5 | G19: =G17-G18 -> -2276190.5 | H19: =H17-H18 -> -1176190.5 | I19: =I17-I18 -> -1176190.5 | ... AC19: =AC17-AC18 -> 63040000
A20: + Амортизация (неденежная статья), руб. | B20: =B16 -> 0 | C20: =C16 -> 476190.48 | D20: =D16 -> 476190.48 | E20: =E16 -> 476190.48 | F20: =F16 -> 476190.48 | G20: =G16 -> 476190.48 | H20: =H16 -> 476190.48 | I20: =I16 -> 476190.48 | ... AC20: =AC16 -> 10000000
A21: − CAPEX, руб. | B21: =Допущения!C16 -> 40000000 | C21: 0 | D21: 0 | E21: 0 | F21: 0 | G21: 0 | H21: 0 | I21: 0 | J21: 0 | K21: 0 | L21: 0 | M21: 0 | N21: 0 | O21: 0 | P21: 0 | Q21: 0 | R21: 0 | S21: 0 | T21: 0 | U21: 0 | V21: 0 | W21: 0 | X21: 0 | Y21: 0 | Z21: 0 | AA21: =Допущения!C18 -> 30000000 | AB21: 0 | AC21: 0
A22: Дебиторская задолженность (баланс), руб. | B22: 0 | C22: =C10*Допущения!$C$33/Допущения!$C$31 -> 0 | D22: =D10*Допущения!$C$33/Допущения!$C$31 -> 4500000 | E22: =E10*Допущения!$C$33/Допущения!$C$31 -> 4500000 | F22: =F10*Допущения!$C$33/Допущения!$C$31 -> 9000000 | G22: =G10*Допущения!$C$33/Допущения!$C$31 -> 9000000 | H22: =H10*Допущения!$C$33/Допущения!$C$31 -> 13500000 | I22: =I10*Допущения!$C$33/Допущения!$C$31 -> 13500000 | J22: =J10*Допущения!$C$33/Допущения!$C$31 -> 18000000 | ... Z22: =Z10*Допущения!$C$33/Допущения!$C$31 -> 27000000 | AA22: =AA10*Допущения!$C$33/Допущения!$C$42 -> 45000000 | AB22: =AB10*Допущения!$C$33/Допущения!$C$42 -> 45000000 | AC22: =AC10*Допущения!$C$33/Допущения!$C$42 -> 47250000
A23: Запасы, руб. | B23: =B12*(Допущения!$C$32/Допущения!$C$31) -> 0 | C23: =C12*(Допущения!$C$32/Допущения!$C$31) -> 0 | D23: =D12*(Допущения!$C$32/Допущения!$C$31) -> 2850000 | E23: =E12*(Допущения!$C$32/Допущения!$C$31) -> 2850000 | F23: =F12*(Допущения!$C$32/Допущения!$C$31) -> 5700000 | G23: =G12*(Допущения!$C$32/Допущения!$C$31) -> 5700000 | H23: =H12*(Допущения!$C$32/Допущения!$C$31) -> 8550000 | I23: =I12*(Допущения!$C$32/Допущения!$C$31) -> 8550000 | ... Z23: =Z12*(Допущения!$C$32/Допущения!$C$31) -> 17100000 | AA23: =AA12*(Допущения!$C$32/Допущения!$C$42) -> 28500000 | AB23: =AB12*(Допущения!$C$32/Допущения!$C$42) -> 28500000 | AC23: =AC12*(Допущения!$C$32/Допущения!$C$42) -> 28500000
A24: Кредиторская задолженность (поставщики), руб. | B24: =B12*(Допущения!$C$34/Допущения!$C$31) -> 0 | C24: =C12*(Допущения!$C$34/Допущения!$C$31) -> 0 | D24: =D12*(Допущения!$C$34/Допущения!$C$31) -> 2850000 | E24: =E12*(Допущения!$C$34/Допущения!$C$31) -> 2850000 | F24: =F12*(Допущения!$C$34/Допущения!$C$31) -> 5700000 | G24: =G12*(Допущения!$C$34/Допущения!$C$31) -> 5700000 | H24: =H12*(Допущения!$C$34/Допущения!$C$31) -> 8550000 | I24: =I12*(Допущения!$C$34/Допущения!$C$31) -> 8550000 | ... Z24: =Z12*(Допущения!$C$34/Допущения!$C$31) -> 17100000 | AA24: =AA12*(Допущения!$C$34/Допущения!$C$42) -> 28500000 | AB24: =AB12*(Допущения!$C$34/Допущения!$C$42) -> 28500000 | AC24: =AC12*(Допущения!$C$34/Допущения!$C$42) -> 28500000
A25: Чистый оборотный капитал (NWC), руб. | B25: 0 | C25: =C22+C23-C24 -> 0 | D25: =D22+D23-D24 -> 4500000 | E25: =E22+E23-E24 -> 4500000 | F25: =F22+F23-F24 -> 9000000 | G25: =G22+G23-G24 -> 9000000 | H25: =H22+H23-H24 -> 13500000 | I25: =I22+I23-I24 -> 13500000 | J25: =J22+J23-J24 -> 18000000 | ... AC25: =AC22+AC23-AC24 -> 47250000
A26: − Изменение NWC, руб. | C26: =C25-B25 -> 0 | D26: =D25-C25 -> 4500000 | E26: =E25-D25 -> 0 | F26: =F25-E25 -> 4500000 | G26: =G25-F25 -> 0 | H26: =H25-G25 -> 4500000 | I26: =I25-H25 -> 0 | J26: =J25-I25 -> 4500000 | ... AC26: =AC25-AB25 -> 2250000
A27: Свободный денежный поток (FCF), руб. | B27: =B19+B20-B21-B26 -> -40000000 | C27: =C19+C20-C21-C26 -> -4000000 | D27: =D19+D20-D21-D26 -> -7400000 | E27: =E19+E20-E21-E26 -> -2900000 | F27: =F19+F20-F21-F26 -> -6300000 | G27: =G19+G20-G21-G26 -> -1800000 | H27: =H19+H20-H21-H26 -> -5200000 | I27: =I19+I20-I21-I26 -> -700000 | ... AC27: =AC19+AC20-AC21-AC26 -> 70790000
A28: Коэффициент дисконтирования | B28: 1 | C28: =1/(1+Допущения!C8)^1 -> 0.98492138 | D28: =1/(1+Допущения!C8)^2 -> 0.97007012 | E28: =1/(1+Допущения!C8)^3 -> 0.95544279 | F28: =1/(1+Допущения!C8)^4 -> 0.94103603 | G28: =1/(1+Допущения!C8)^5 -> 0.9268465 | H28: =1/(1+Допущения!C8)^6 -> 0.91287093 | I28: =1/(1+Допущения!C8)^7 -> 0.89910609 | J28: =1/(1+Допущения!C8)^8 -> 0.88554881 | K28: =1/(1+Допущения!C8)^9 -> 0.87219595 | L28: =1/(1+Допущения!C8)^10 -> 0.85904443 | M28: =1/(1+Допущения!C8)^11 -> 0.84609123 | N28: =1/(1+Допущения!C8)^12 -> 0.83333333 | O28: =1/(1+Допущения!C8)^13 -> 0.82076781 | P28: =1/(1+Допущения!C8)^14 -> 0.80839176 | Q28: =1/(1+Допущения!C8)^15 -> 0.79620233 | R28: =1/(1+Допущения!C8)^16 -> 0.78419669 | S28: =1/(1+Допущения!C8)^17 -> 0.77237208 | T28: =1/(1+Допущения!C8)^18 -> 0.76072577 | U28: =1/(1+Допущения!C8)^19 -> 0.74925508 | V28: =1/(1+Допущения!C8)^20 -> 0.73795734 | W28: =1/(1+Допущения!C8)^21 -> 0.72682996 | X28: =1/(1+Допущения!C8)^22 -> 0.71587036 | Y28: =1/(1+Допущения!C8)^23 -> 0.70507602 | Z28: =1/(1+Допущения!C8)^24 -> 0.69444444 | AA28: =1/(1+Допущения!C7)^3 -> 0.5787037 | AB28: =1/(1+Допущения!C7)^4 -> 0.48225309 | AC28: =1/(1+Допущения!C7)^5 -> 0.40187757
A29: Дисконтированный FCF, руб. | B29: =B27*B28 -> -40000000 | C29: =C27*C28 -> -3939685.5 | D29: =D27*D28 -> -7178518.9 | E29: =E27*E28 -> -2770784.1 | F29: =F27*F28 -> -5928527 | G29: =G27*G28 -> -1668323.7 | H29: =H27*H28 -> -4746928.8 | I29: =I27*I28 -> -629374.26 | ... AC29: =AC27*AC28 -> 28448913
A30: Накопленный FCF, руб. | B30: =B27 -> -40000000 | C30: =B30+C27 -> -44000000 | D30: =C30+D27 -> -51400000 | E30: =D30+E27 -> -54300000 | F30: =E30+F27 -> -60600000 | G30: =F30+G27 -> -62400000 | H30: =G30+H27 -> -67600000 | I30: =H30+I27 -> -68300000 | J30: =I30+J27 -> -72400000 | ... AC30: =AB30+AC27 -> 89938571
A31: Накопленный дисконтированный FCF, руб. | B31: =B29 -> -40000000 | C31: =B31+C29 -> -43939686 | D31: =C31+D29 -> -51118204 | E31: =D31+E29 -> -53888988 | F31: =E31+F29 -> -59817515 | G31: =F31+G29 -> -61485839 | H31: =G31+H29 -> -66232768 | I31: =H31+I29 -> -66862142 | J31: =I31+J29 -> -70492892 | ... AC31: =AB31+AC29 -> 8881137.9
A32: NPV | B32: =AC31 -> 8881137.9
A34: Вспомогательный расчёт IRR (перебор ставок)
A35: Лет с начала проекта | B35: =(B6-B6)/365.25 -> 0 | C35: =(C6-B6)/365.25 -> 0.082135524 | D35: =(D6-B6)/365.25 -> 0.1670089 | E35: =(E6-B6)/365.25 -> 0.24914442 | F35: =(F6-B6)/365.25 -> 0.3340178 | G35: =(G6-B6)/365.25 -> 0.41889117 | H35: =(H6-B6)/365.25 -> 0.49555099 | I35: =(I6-B6)/365.25 -> 0.58042437 | J35: =(J6-B6)/365.25 -> 0.66255989 | K35: =(K6-B6)/365.25 -> 0.74743326 | L35: =(L6-B6)/365.25 -> 0.82956879 | M35: =(M6-B6)/365.25 -> 0.91444216 | N35: =(N6-B6)/365.25 -> 0.99931554 | O35: =(O6-B6)/365.25 -> 1.0814511 | P35: =(P6-B6)/365.25 -> 1.1663244 | Q35: =(Q6-B6)/365.25 -> 1.24846 | R35: =(R6-B6)/365.25 -> 1.3333333 | S35: =(S6-B6)/365.25 -> 1.4182067 | T35: =(T6-B6)/365.25 -> 1.4976044 | U35: =(U6-B6)/365.25 -> 1.5824778 | V35: =(V6-B6)/365.25 -> 1.6646133 | W35: =(W6-B6)/365.25 -> 1.7494867 | X35: =(X6-B6)/365.25 -> 1.8316222 | Y35: =(Y6-B6)/365.25 -> 1.9164956 | Z35: =(Z6-B6)/365.25 -> 2.0013689 | AA35: =(AA6-B6)/365.25 -> 3.0006845 | AB35: =(AB6-B6)/365.25 -> 4 | AC35: =(AC6-B6)/365.25 -> 4.9993155
A37: Ставка (перебор) | B37: 0 | C37: 0.01 | D37: 0.02 | E37: 0.03 | F37: 0.04 | G37: 0.05 | H37: 0.06 | I37: 0.07 | J37: 0.08 | K37: 0.09 | L37: 0.1 | M37: 0.11 | N37: 0.12 | O37: 0.13 | P37: 0.14 | Q37: 0.15 | R37: 0.16 | S37: 0.17 | T37: 0.18 | U37: 0.19 | V37: 0.2 | W37: 0.21 | X37: 0.22 | Y37: 0.23 | Z37: 0.24 | AA37: 0.25 | AB37: 0.26 | AC37: 0.27
A38: NPV при этой ставке | B38: =SUMPRODUCT(B27:AC27,(1+B37)^(-B35:AC35)) -> 89938571 | C38: =SUMPRODUCT(B27:AC27,(1+C37)^(-B35:AC35)) -> 83647432 | D38: =SUMPRODUCT(B27:AC27,(1+D37)^(-B35:AC35)) -> 77684988 | E38: =SUMPRODUCT(B27:AC27,(1+E37)^(-B35:AC35)) -> 72030808 | F38: =SUMPRODUCT(B27:AC27,(1+F37)^(-B35:AC35)) -> 66665926 | G38: =SUMPRODUCT(B27:AC27,(1+G37)^(-B35:AC35)) -> 61572720 | H38: =SUMPRODUCT(B27:AC27,(1+H37)^(-B35:AC35)) -> 56734807 | I38: =SUMPRODUCT(B27:AC27,(1+I37)^(-B35:AC35)) -> 52136945 | J38: =SUMPRODUCT(B27:AC27,(1+J37)^(-B35:AC35)) -> 47764943 | K38: =SUMPRODUCT(B27:AC27,(1+K37)^(-B35:AC35)) -> 43605576 | L38: =SUMPRODUCT(B27:AC27,(1+L37)^(-B35:AC35)) -> 39646515 | M38: =SUMPRODUCT(B27:AC27,(1+M37)^(-B35:AC35)) -> 35876257 | N38: =SUMPRODUCT(B27:AC27,(1+N37)^(-B35:AC35)) -> 32284063 | O38: =SUMPRODUCT(B27:AC27,(1+O37)^(-B35:AC35)) -> 28859898 | P38: =SUMPRODUCT(B27:AC27,(1+P37)^(-B35:AC35)) -> 25594382 | Q38: =SUMPRODUCT(B27:AC27,(1+Q37)^(-B35:AC35)) -> 22478742 | R38: =SUMPRODUCT(B27:AC27,(1+R37)^(-B35:AC35)) -> 19504764 | S38: =SUMPRODUCT(B27:AC27,(1+S37)^(-B35:AC35)) -> 16664757 | T38: =SUMPRODUCT(B27:AC27,(1+T37)^(-B35:AC35)) -> 13951511 | U38: =SUMPRODUCT(B27:AC27,(1+U37)^(-B35:AC35)) -> 11358266 | V38: =SUMPRODUCT(B27:AC27,(1+V37)^(-B35:AC35)) -> 8878682 | W38: =SUMPRODUCT(B27:AC27,(1+W37)^(-B35:AC35)) -> 6506803.6 | X38: =SUMPRODUCT(B27:AC27,(1+X37)^(-B35:AC35)) -> 4237038.6 | Y38: =SUMPRODUCT(B27:AC27,(1+Y37)^(-B35:AC35)) -> 2064131.2 | Z38: =SUMPRODUCT(B27:AC27,(1+Z37)^(-B35:AC35)) -> -16860.967 | AA38: =SUMPRODUCT(B27:AC27,(1+AA37)^(-B35:AC35)) -> -2010587.7 | AB38: =SUMPRODUCT(B27:AC27,(1+AB37)^(-B35:AC35)) -> -3921425.9 | AC38: =SUMPRODUCT(B27:AC27,(1+AC37)^(-B35:AC35)) -> -5753498
A39: Индекс последней ставки с NPV>=0 | B39: =SUMPRODUCT(--(B38:AC38>=0)) -> 24
A40: IRR (линейная интерполяция), год. | B40: =INDEX(B37:AC37,B39)+(0-INDEX(B38:AC38,B39))/(INDEX(B38:AC38,B39+1)-INDEX(B38:AC38,B39))*(INDEX(B37:AC37,B39+1)-INDEX(B37:AC37,B39)) -> 0.23991898

Sheet Сценарии
A1: Сценарии: Пессимистичный / База / Оптимистичный
A2: Упрощённое погодовое сравнение — множители применяются к компонентам выручки и затрат базового сценария (лист «Модель»), без повторного построения полной помесячной модели.
A4: 1. Множители сценария
B5: Пессимистичный | C5: База | D5: Оптимистичный
A6: Объём продаж | B6: 0.7 | C6: 1 | D6: 1.3
A7: Цена | B7: 0.95 | C7: 1 | D7: 1.05
A8: Переменные затраты/ед. | B8: 1.1 | C8: 1 | D8: 0.95
A9: Постоянные затраты (произв.+админ.+маркетинг) | B9: 1.05 | C9: 1 | D9: 1
A11: 2. EBIT по годам, руб.
B12: Пессимистичный | C12: База | D12: Оптимистичный
A13: Год 1 | B13: =(SUM(Модель!C10:N10))*B$6*B$7-(SUM(Модель!C12:N12))*B$6*B$8-(SUM(Модель!C14:N14))*B$9-(SUM(Модель!C15:N15))*B$9-(SUM(Модель!C16:N16)) -> -36962286 | C13: =(SUM(Модель!C10:N10))*C$6*C$7-(SUM(Модель!C12:N12))*C$6*C$8-(SUM(Модель!C14:N14))*C$9-(SUM(Модель!C15:N15))*C$9-(SUM(Модель!C16:N16)) -> -14114286 | D13: =(SUM(Модель!C10:N10))*D$6*D$7-(SUM(Модель!C12:N12))*D$6*D$8-(SUM(Модель!C14:N14))*D$9-(SUM(Модель!C15:N15))*D$9-(SUM(Модель!C16:N16)) -> 9231714.3
A14: Год 2 | B14: =(SUM(Модель!O10:Z10))*B$6*B$7-(SUM(Модель!O12:Z12))*B$6*B$8-(SUM(Модель!O14:Z14))*B$9-(SUM(Модель!O15:Z15))*B$9-(SUM(Модель!O16:Z16)) -> -17810286 | C14: =(SUM(Модель!O10:Z10))*C$6*C$7-(SUM(Модель!O12:Z12))*C$6*C$8-(SUM(Модель!O14:Z14))*C$9-(SUM(Модель!O15:Z15))*C$9-(SUM(Модель!O16:Z16)) -> 25485714 | D14: =(SUM(Модель!O10:Z10))*D$6*D$7-(SUM(Модель!O12:Z12))*D$6*D$8-(SUM(Модель!O14:Z14))*D$9-(SUM(Модель!O15:Z15))*D$9-(SUM(Модель!O16:Z16)) -> 72177714
A15: Год 3 | B15: =(SUM(Модель!AA10))*B$6*B$7-(SUM(Модель!AA12))*B$6*B$8-(SUM(Модель!AA14))*B$9-(SUM(Модель!AA15))*B$9-(SUM(Модель!AA16)) -> -10420000 | C15: =(SUM(Модель!AA10))*C$6*C$7-(SUM(Модель!AA12))*C$6*C$8-(SUM(Модель!AA14))*C$9-(SUM(Модель!AA15))*C$9-(SUM(Модель!AA16)) -> 60800000 | D15: =(SUM(Модель!AA10))*D$6*D$7-(SUM(Модель!AA12))*D$6*D$8-(SUM(Модель!AA14))*D$9-(SUM(Модель!AA15))*D$9-(SUM(Модель!AA16)) -> 138620000
A16: Год 4 | B16: =(SUM(Модель!AB10))*B$6*B$7-(SUM(Модель!AB12))*B$6*B$8-(SUM(Модель!AB14))*B$9-(SUM(Модель!AB15))*B$9-(SUM(Модель!AB16)) -> -10420000 | C16: =(SUM(Модель!AB10))*C$6*C$7-(SUM(Модель!AB12))*C$6*C$8-(SUM(Модель!AB14))*C$9-(SUM(Модель!AB15))*C$9-(SUM(Модель!AB16)) -> 60800000 | D16: =(SUM(Модель!AB10))*D$6*D$7-(SUM(Модель!AB12))*D$6*D$8-(SUM(Модель!AB14))*D$9-(SUM(Модель!AB15))*D$9-(SUM(Модель!AB16)) -> 138620000
A17: Год 5 | B17: =(SUM(Модель!AC10))*B$6*B$7-(SUM(Модель!AC12))*B$6*B$8-(SUM(Модель!AC14))*B$9-(SUM(Модель!AC15))*B$9-(SUM(Модель!AC16)) -> 1550000 | C17: =(SUM(Модель!AC10))*C$6*C$7-(SUM(Модель!AC12))*C$6*C$8-(SUM(Модель!AC14))*C$9-(SUM(Модель!AC15))*C$9-(SUM(Модель!AC16)) -> 78800000 | D17: =(SUM(Модель!AC10))*D$6*D$7-(SUM(Модель!AC12))*D$6*D$8-(SUM(Модель!AC14))*D$9-(SUM(Модель!AC15))*D$9-(SUM(Модель!AC16)) -> 163190000
A19: 3. Итоговые метрики (EBIT после налога, без CAPEX/оборотного капитала — для быстрого сравнения риска)
A20: Сумма чистой прибыли за 5 лет, руб. | B20: =(B13+B14+B15+B16+B17)*(1-Допущения!C37) -> -59250057 | C20: =(C13+C14+C15+C16+C17)*(1-Допущения!C37) -> 1.6941714e+08 | D20: =(D13+D14+D15+D16+D17)*(1-Допущения!C37) -> 4.1747154e+08
A21: Средний годовой EBIT, руб. | B21: =(B13+B14+B15+B16+B17)/5 -> -14812514 | C21: =(C13+C14+C15+C16+C17)/5 -> 42354286 | D21: =(D13+D14+D15+D16+D17)/5 -> 1.0436789e+08
A23: Полный NPV/IRR с учётом CAPEX и оборотного капитала считается только для Базового сценария (листы «Модель» и «Итоги») — сравнение выше показывает направление и масштаб риска по операционной прибыли, а не альтернативный NPV.

Sheet Чувствительность
A1: Чувствительность NPV к цене и ставке дисконтирования
A2: Упрощённый расчёт на годовой основе: цена и оборотный капитал масштабируются по годам (а не помесячно, как в базовой модели), поэтому центральная ячейка (цена 100%, ставка 20%) может на 1–3% отличаться от точного NPV на листе «Итоги» — из-за разной гранулярности дисконтирования, а не из-за ошибки.
A5: Вспомогательные годовые данные (база, множитель цены = 100%)
A6: EBIT баз., Год 1 | B6: =SUM(Модель!C17:N17) -> -14114286
A7: EBIT баз., Год 2 | B7: =SUM(Модель!O17:Z17) -> 25485714
A8: EBIT баз., Год 3 | B8: =Модель!AA17 -> 60800000
A9: EBIT баз., Год 4 | B9: =Модель!AB17 -> 60800000
A10: EBIT баз., Год 5 | B10: =Модель!AC17 -> 78800000
A11: Выручка баз., Год 1 | B11: =SUM(Модель!C10:N10) -> 108000000
A12: Выручка баз., Год 2 | B12: =SUM(Модель!O10:Z10) -> 216000000
A13: Выручка баз., Год 3 | B13: =Модель!AA10 -> 360000000
A14: Выручка баз., Год 4 | B14: =Модель!AB10 -> 360000000
A15: Выручка баз., Год 5 | B15: =Модель!AC10 -> 378000000
A17: Сетка: ИТОГОВЫЙ NPV (5 лет + консервативная остаточная стоимость), руб.
A18: Цена \ Ставка дисконт. | B18: 0.15 | C18: 0.18 | D18: 0.2 | E18: 0.22 | F18: 0.25
A19: 0.8 | B19: =-Допущения!C16+(((($B$6+($A19-1)*$B$11))*(1-Допущения!C37)+SUM(Модель!C16:N16)-((($B$11*$A19))*Допущения!C33/360-(0)*Допущения!C33/360)))/(1+B$18)^1+(((($B$7+($A19-1)*$B$12))*(1-Допущения!C37)+SUM(Модель!O16:Z16)-((($B$12*$A19))*Допущения!C33/360-(($B$11*$A19))*Допущения!C33/360)))/(1+B$18)^2+(((($B$8+($A19-1)*$B$13))*(1-Допущения!C37)+Модель!AA16-((($B$13*$A19))*Допущения!C33/360-(($B$12*$A19))*Допущения!C33/360)))/(1+B$18)^3+(((($B$9+($A19-1)*$B$14))*(1-Допущения!C37)+Модель!AB16-((($B$14*$A19))*Допущения!C33/360-(($B$13*$A19))*Допущения!C33/360)))/(1+B$18)^4+(((($B$10+($A19-1)*$B$15))*(1-Допущения!C37)+Модель!AC16-((($B$15*$A19))*Допущения!C33/360-(($B$14*$A19))*Допущения!C33/360)))/(1+B$18)^5-(Допущения!C18)/(1+B$18)^3+((($B$10+($A19-1)*$B$15)*(1-Допущения!C37)+Модель!AC16)/(1+B$18)^6+(($B$10+($A19-1)*$B$15)*(1-Допущения!C37)+Модель!AC16)/(1+B$18)^7) -> -96242102 | C19: =-Допущения!C16+(((($B$6+($A19-1)*$B$11))*(1-Допущения!C37)+SUM(Модель!C16:N16)-((($B$11*$A19))*Допущения!C33/360-(0)*Допущения!C33/360)))/(1+C$18)^1+(((($B$7+($A19-1)*$B$12))*(1-Допущения!C37)+SUM(Модель!O16:Z16)-((($B$12*$A19))*Допущения!C33/360-(($B$11*$A19))*Допущения!C33/360)))/(1+C$18)^2+(((($B$8+($A19-1)*$B$13))*(1-Допущения!C37)+Модель!AA16-((($B$13*$A19))*Допущения!C33/360-(($B$12*$A19))*Допущения!C33/360)))/(1+C$18)^3+(((($B$9+($A19-1)*$B$14))*(1-Допущения!C37)+Модель!AB16-((($B$14*$A19))*Допущения!C33/360-(($B$13*$A19))*Допущения!C33/360)))/(1+C$18)^4+(((($B$10+($A19-1)*$B$15))*(1-Допущения!C37)+Модель!AC16-((($B$15*$A19))*Допущения!C33/360-(($B$14*$A19))*Допущения!C33/360)))/(1+C$18)^5-(Допущения!C18)/(1+C$18)^3+((($B$10+($A19-1)*$B$15)*(1-Допущения!C37)+Модель!AC16)/(1+C$18)^6+(($B$10+($A19-1)*$B$15)*(1-Допущения!C37)+Модель!AC16)/(1+C$18)^7) -> -94908183 | D19: =-Допущения!C16+(((($B$6+($A19-1)*$B$11))*(1-Допущения!C37)+SUM(Модель!C16:N16)-((($B$11*$A19))*Допущения!C33/360-(0)*Допущения!C33/360)))/(1+D$18)^1+(((($B$7+($A19-1)*$B$12))*(1-Допущения!C37)+SUM(Модель!O16:Z16)-((($B$12*$A19))*Допущения!C33/360-(($B$11*$A19))*Допущения!C33/360)))/(1+D$18)^2+(((($B$8+($A19-1)*$B$13))*(1-Допущения!C37)+Модель!AA16-((($B$13*$A19))*Допущения!C33/360-(($B$12*$A19))*Допущения!C33/360)))/(1+D$18)^3+(((($B$9+($A19-1)*$B$14))*(1-Допущения!C37)+Модель!AB16-((($B$14*$A19))*Допущения!C33/360-(($B$13*$A19))*Допущения!C33/360)))/(1+D$18)^4+(((($B$10+($A19-1)*$B$15))*(1-Допущения!C37)+Модель!AC16-((($B$15*$A19))*Допущения!C33/360-(($B$14*$A19))*Допущения!C33/360)))/(1+D$18)^5-(Допущения!C18)/(1+D$18)^3+((($B$10+($A19-1)*$B$15)*(1-Допущения!C37)+Модель!AC16)/(1+D$18)^6+(($B$10+($A19-1)*$B$15)*(1-Допущения!C37)+Модель!AC16)/(1+D$18)^7) -> -93975898 | E19: =-Допущения!C16+(((($B$6+($A19-1)*$B$11))*(1-Допущения!C37)+SUM(Модель!C16:N16)-((($B$11*$A19))*Допущения!C33/360-(0)*Допущения!C33/360)))/(1+E$18)^1+(((($B$7+($A19-1)*$B$12))*(1-Допущения!C37)+SUM(Модель!O16:Z16)-((($B$12*$A19))*Допущения!C33/360-(($B$11*$A19))*Допущения!C33/360)))/(1+E$18)^2+(((($B$8+($A19-1)*$B$13))*(1-Допущения!C37)+Модель!AA16-((($B$13*$A19))*Допущения!C33/360-(($B$12*$A19))*Допущения!C33/360)))/(1+E$18)^3+(((($B$9+($A19-1)*$B$14))*(1-Допущения!C37)+Модель!AB16-((($B$14*$A19))*Допущения!C33/360-(($B$13*$A19))*Допущения!C33/360)))/(1+E$18)^4+(((($B$10+($A19-1)*$B$15))*(1-Допущения!C37)+Модель!AC16-((($B$15*$A19))*Допущения!C33/360-(($B$14*$A19))*Допущения!C33/360)))/(1+E$18)^5-(Допущения!C18)/(1+E$18)^3+((($B$10+($A19-1)*$B$15)*(1-Допущения!C37)+Модель!AC16)/(1+E$18)^6+(($B$10+($A19-1)*$B$15)*(1-Допущения!C37)+Модель!AC16)/(1+E$18)^7) -> -93022531 | F19: =-Допущения!C16+(((($B$6+($A19-1)*$B$11))*(1-Допущения!C37)+SUM(Модель!C16:N16)-((($B$11*$A19))*Допущения!C33/360-(0)*Допущения!C33/360)))/(1+F$18)^1+(((($B$7+($A19-1)*$B$12))*(1-Допущения!C37)+SUM(Модель!O16:Z16)-((($B$12*$A19))*Допущения!C33/360-(($B$11*$A19))*Допущения!C33/360)))/(1+F$18)^2+(((($B$8+($A19-1)*$B$13))*(1-Допущения!C37)+Модель!AA16-((($B$13*$A19))*Допущения!C33/360-(($B$12*$A19))*Допущения!C33/360)))/(1+F$18)^3+(((($B$9+($A19-1)*$B$14))*(1-Допущения!C37)+Модель!AB16-((($B$14*$A19))*Допущения!C33/360-(($B$13*$A19))*Допущения!C33/360)))/(1+F$18)^4+(((($B$10+($A19-1)*$B$15))*(1-Допущения!C37)+Модель!AC16-((($B$15*$A19))*Допущения!C33/360-(($B$14*$A19))*Допущения!C33/360)))/(1+F$18)^5-(Допущения!C18)/(1+F$18)^3+((($B$10+($A19-1)*$B$15)*(1-Допущения!C37)+Модель!AC16)/(1+F$18)^6+(($B$10+($A19-1)*$B$15)*(1-Допущения!C37)+Модель!AC16)/(1+F$18)^7) -> -91572233
A20: 0.9 | B20: =-Допущения!C16+(((($B$6+($A20-1)*$B$11))*(1-Допущения!C37)+SUM(Модель!C16:N16)-((($B$11*$A20))*Допущения!C33/360-(0)*Допущения!C33/360)))/(1+B$18)^1+(((($B$7+($A20-1)*$B$12))*(1-Допущения!C37)+SUM(Модель!O16:Z16)-((($B$12*$A20))*Допущения!C33/360-(($B$11*$A20))*Допущения!C33/360)))/(1+B$18)^2+(((($B$8+($A20-1)*$B$13))*(1-Допущения!C37)+Модель!AA16-((($B$13*$A20))*Допущения!C33/360-(($B$12*$A20))*Допущения!C33/360)))/(1+B$18)^3+(((($B$9+($A20-1)*$B$14))*(1-Допущения!C37)+Модель!AB16-((($B$14*$A20))*Допущения!C33/360-(($B$13*$A20))*Допущения!C33/360)))/(1+B$18)^4+(((($B$10+($A20-1)*$B$15))*(1-Допущения!C37)+Модель!AC16-((($B$15*$A20))*Допущения!C33/360-(($B$14*$A20))*Допущения!C33/360)))/(1+B$18)^5-(Допущения!C18)/(1+B$18)^3+((($B$10+($A20-1)*$B$15)*(1-Допущения!C37)+Модель!AC16)/(1+B$18)^6+(($B$10+($A20-1)*$B$15)*(1-Допущения!C37)+Модель!AC16)/(1+B$18)^7) -> -4273489.2 | C20: =-Допущения!C16+(((($B$6+($A20-1)*$B$11))*(1-Допущения!C37)+SUM(Модель!C16:N16)-((($B$11*$A20))*Допущения!C33/360-(0)*Допущения!C33/360)))/(1+C$18)^1+(((($B$7+($A20-1)*$B$12))*(1-Допущения!C37)+SUM(Модель!O16:Z16)-((($B$12*$A20))*Допущения!C33/360-(($B$11*$A20))*Допущения!C33/360)))/(1+C$18)^2+(((($B$8+($A20-1)*$B$13))*(1-Допущения!C37)+Модель!AA16-((($B$13*$A20))*Допущения!C33/360-(($B$12*$A20))*Допущения!C33/360)))/(1+C$18)^3+(((($B$9+($A20-1)*$B$14))*(1-Допущения!C37)+Модель!AB16-((($B$14*$A20))*Допущения!C33/360-(($B$13*$A20))*Допущения!C33/360)))/(1+C$18)^4+(((($B$10+($A20-1)*$B$15))*(1-Допущения!C37)+Модель!AC16-((($B$15*$A20))*Допущения!C33/360-(($B$14*$A20))*Допущения!C33/360)))/(1+C$18)^5-(Допущения!C18)/(1+C$18)^3+((($B$10+($A20-1)*$B$15)*(1-Допущения!C37)+Модель!AC16)/(1+C$18)^6+(($B$10+($A20-1)*$B$15)*(1-Допущения!C37)+Модель!AC16)/(1+C$18)^7) -> -12187010 | D20: =-Допущения!C16+(((($B$6+($A20-1)*$B$11))*(1-Допущения!C37)+SUM(Модель!C16:N16)-((($B$11*$A20))*Допущения!C33/360-(0)*Допущения!C33/360)))/(1+D$18)^1+(((($B$7+($A20-1)*$B$12))*(1-Допущения!C37)+SUM(Модель!O16:Z16)-((($B$12*$A20))*Допущения!C33/360-(($B$11*$A20))*Допущения!C33/360)))/(1+D$18)^2+(((($B$8+($A20-1)*$B$13))*(1-Допущения!C37)+Модель!AA16-((($B$13*$A20))*Допущения!C33/360-(($B$12*$A20))*Допущения!C33/360)))/(1+D$18)^3+(((($B$9+($A20-1)*$B$14))*(1-Допущения!C37)+Модель!AB16-((($B$14*$A20))*Допущения!C33/360-(($B$13*$A20))*Допущения!C33/360)))/(1+D$18)^4+(((($B$10+($A20-1)*$B$15))*(1-Допущения!C37)+Модель!AC16-((($B$15*$A20))*Допущения!C33/360-(($B$14*$A20))*Допущения!C33/360)))/(1+D$18)^5-(Допущения!C18)/(1+D$18)^3+((($B$10+($A20-1)*$B$15)*(1-Допущения!C37)+Модель!AC16)/(1+D$18)^6+(($B$10+($A20-1)*$B$15)*(1-Допущения!C37)+Модель!AC16)/(1+D$18)^7) -> -16695410 | E20: =-Допущения!C16+(((($B$6+($A20-1)*$B$11))*(1-Допущения!C37)+SUM(Модель!C16:N16)-((($B$11*$A20))*Допущения!C33/360-(0)*Допущения!C33/360)))/(1+E$18)^1+(((($B$7+($A20-1)*$B$12))*(1-Допущения!C37)+SUM(Модель!O16:Z16)-((($B$12*$A20))*Допущения!C33/360-(($B$11*$A20))*Допущения!C33/360)))/(1+E$18)^2+(((($B$8+($A20-1)*$B$13))*(1-Допущения!C37)+Модель!AA16-((($B$13*$A20))*Допущения!C33/360-(($B$12*$A20))*Допущения!C33/360)))/(1+E$18)^3+(((($B$9+($A20-1)*$B$14))*(1-Допущения!C37)+Модель!AB16-((($B$14*$A20))*Допущения!C33/360-(($B$13*$A20))*Допущения!C33/360)))/(1+E$18)^4+(((($B$10+($A20-1)*$B$15))*(1-Допущения!C37)+Модель!AC16-((($B$15*$A20))*Допущения!C33/360-(($B$14*$A20))*Допущения!C33/360)))/(1+E$18)^5-(Допущения!C18)/(1+E$18)^3+((($B$10+($A20-1)*$B$15)*(1-Допущения!C37)+Модель!AC16)/(1+E$18)^6+(($B$10+($A20-1)*$B$15)*(1-Допущения!C37)+Модель!AC16)/(1+E$18)^7) -> -20680998 | F20: =-Допущения!C16+(((($B$6+($A20-1)*$B$11))*(1-Допущения!C37)+SUM(Модель!C16:N16)-((($B$11*$A20))*Допущения!C33/360-(0)*Допущения!C33/360)))/(1+F$18)^1+(((($B$7+($A20-1)*$B$12))*(1-Допущения!C37)+SUM(Модель!O16:Z16)-((($B$12*$A20))*Допущения!C33/360-(($B$11*$A20))*Допущения!C33/360)))/(1+F$18)^2+(((($B$8+($A20-1)*$B$13))*(1-Допущения!C37)+Модель!AA16-((($B$13*$A20))*Допущения!C33/360-(($B$12*$A20))*Допущения!C33/360)))/(1+F$18)^3+(((($B$9+($A20-1)*$B$14))*(1-Допущения!C37)+Модель!AB16-((($B$14*$A20))*Допущения!C33/360-(($B$13*$A20))*Допущения!C33/360)))/(1+F$18)^4+(((($B$10+($A20-1)*$B$15))*(1-Допущения!C37)+Модель!AC16-((($B$15*$A20))*Допущения!C33/360-(($B$14*$A20))*Допущения!C33/360)))/(1+F$18)^5-(Допущения!C18)/(1+F$18)^3+((($B$10+($A20-1)*$B$15)*(1-Допущения!C37)+Модель!AC16)/(1+F$18)^6+(($B$10+($A20-1)*$B$15)*(1-Допущения!C37)+Модель!AC16)/(1+F$18)^7) -> -25820216
A21: 1 | B21: =-Допущения!C16+(((($B$6+($A21-1)*$B$11))*(1-Допущения!C37)+SUM(Модель!C16:N16)-((($B$11*$A21))*Допущения!C33/360-(0)*Допущения!C33/360)))/(1+B$18)^1+(((($B$7+($A21-1)*$B$12))*(1-Допущения!C37)+SUM(Модель!O16:Z16)-((($B$12*$A21))*Допущения!C33/360-(($B$11*$A21))*Допущения!C33/360)))/(1+B$18)^2+(((($B$8+($A21-1)*$B$13))*(1-Допущения!C37)+Модель!AA16-((($B$13*$A21))*Допущения!C33/360-(($B$12*$A21))*Допущения!C33/360)))/(1+B$18)^3+(((($B$9+($A21-1)*$B$14))*(1-Допущения!C37)+Модель!AB16-((($B$14*$A21))*Допущения!C33/360-(($B$13*$A21))*Допущения!C33/360)))/(1+B$18)^4+(((($B$10+($A21-1)*$B$15))*(1-Допущения!C37)+Модель!AC16-((($B$15*$A21))*Допущения!C33/360-(($B$14*$A21))*Допущения!C33/360)))/(1+B$18)^5-(Допущения!C18)/(1+B$18)^3+((($B$10+($A21-1)*$B$15)*(1-Допущения!C37)+Модель!AC16)/(1+B$18)^6+(($B$10+($A21-1)*$B$15)*(1-Допущения!C37)+Модель!AC16)/(1+B$18)^7) -> 87695124 | C21: =-Допущения!C16+(((($B$6+($A21-1)*$B$11))*(1-Допущения!C37)+SUM(Модель!C16:N16)-((($B$11*$A21))*Допущения!C33/360-(0)*Допущения!C33/360)))/(1+C$18)^1+(((($B$7+($A21-1)*$B$12))*(1-Допущения!C37)+SUM(Модель!O16:Z16)-((($B$12*$A21))*Допущения!C33/360-(($B$11*$A21))*Допущения!C33/360)))/(1+C$18)^2+(((($B$8+($A21-1)*$B$13))*(1-Допущения!C37)+Модель!AA16-((($B$13*$A21))*Допущения!C33/360-(($B$12*$A21))*Допущения!C33/360)))/(1+C$18)^3+(((($B$9+($A21-1)*$B$14))*(1-Допущения!C37)+Модель!AB16-((($B$14*$A21))*Допущения!C33/360-(($B$13*$A21))*Допущения!C33/360)))/(1+C$18)^4+(((($B$10+($A21-1)*$B$15))*(1-Допущения!C37)+Модель!AC16-((($B$15*$A21))*Допущения!C33/360-(($B$14*$A21))*Допущения!C33/360)))/(1+C$18)^5-(Допущения!C18)/(1+C$18)^3+((($B$10+($A21-1)*$B$15)*(1-Допущения!C37)+Модель!AC16)/(1+C$18)^6+(($B$10+($A21-1)*$B$15)*(1-Допущения!C37)+Модель!AC16)/(1+C$18)^7) -> 70534163 | D21: =-Допущения!C16+(((($B$6+($A21-1)*$B$11))*(1-Допущения!C37)+SUM(Модель!C16:N16)-((($B$11*$A21))*Допущения!C33/360-(0)*Допущения!C33/360)))/(1+D$18)^1+(((($B$7+($A21-1)*$B$12))*(1-Допущения!C37)+SUM(Модель!O16:Z16)-((($B$12*$A21))*Допущения!C33/360-(($B$11*$A21))*Допущения!C33/360)))/(1+D$18)^2+(((($B$8+($A21-1)*$B$13))*(1-Допущения!C37)+Модель!AA16-((($B$13*$A21))*Допущения!C33/360-(($B$12*$A21))*Допущения!C33/360)))/(1+D$18)^3+(((($B$9+($A21-1)*$B$14))*(1-Допущения!C37)+Модель!AB16-((($B$14*$A21))*Допущения!C33/360-(($B$13*$A21))*Допущения!C33/360)))/(1+D$18)^4+(((($B$10+($A21-1)*$B$15))*(1-Допущения!C37)+Модель!AC16-((($B$15*$A21))*Допущения!C33/360-(($B$14*$A21))*Допущения!C33/360)))/(1+D$18)^5-(Допущения!C18)/(1+D$18)^3+((($B$10+($A21-1)*$B$15)*(1-Допущения!C37)+Модель!AC16)/(1+D$18)^6+(($B$10+($A21-1)*$B$15)*(1-Допущения!C37)+Модель!AC16)/(1+D$18)^7) -> 60585079 | E21: =-Допущения!C16+(((($B$6+($A21-1)*$B$11))*(1-Допущения!C37)+SUM(Модель!C16:N16)-((($B$11*$A21))*Допущения!C33/360-(0)*Допущения!C33/360)))/(1+E$18)^1+(((($B$7+($A21-1)*$B$12))*(1-Допущения!C37)+SUM(Модель!O16:Z16)-((($B$12*$A21))*Допущения!C33/360-(($B$11*$A21))*Допущения!C33/360)))/(1+E$18)^2+(((($B$8+($A21-1)*$B$13))*(1-Допущения!C37)+Модель!AA16-((($B$13*$A21))*Допущения!C33/360-(($B$12*$A21))*Допущения!C33/360)))/(1+E$18)^3+(((($B$9+($A21-1)*$B$14))*(1-Допущения!C37)+Модель!AB16-((($B$14*$A21))*Допущения!C33/360-(($B$13*$A21))*Допущения!C33/360)))/(1+E$18)^4+(((($B$10+($A21-1)*$B$15))*(1-Допущения!C37)+Модель!AC16-((($B$15*$A21))*Допущения!C33/360-(($B$14*$A21))*Допущения!C33/360)))/(1+E$18)^5-(Допущения!C18)/(1+E$18)^3+((($B$10+($A21-1)*$B$15)*(1-Допущения!C37)+Модель!AC16)/(1+E$18)^6+(($B$10+($A21-1)*$B$15)*(1-Допущения!C37)+Модель!AC16)/(1+E$18)^7) -> 51660535 | F21: =-Допущения!C16+(((($B$6+($A21-1)*$B$11))*(1-Допущения!C37)+SUM(Модель!C16:N16)-((($B$11*$A21))*Допущения!C33/360-(0)*Допущения!C33/360)))/(1+F$18)^1+(((($B$7+($A21-1)*$B$12))*(1-Допущения!C37)+SUM(Модель!O16:Z16)-((($B$12*$A21))*Допущения!C33/360-(($B$11*$A21))*Допущения!C33/360)))/(1+F$18)^2+(((($B$8+($A21-1)*$B$13))*(1-Допущения!C37)+Модель!AA16-((($B$13*$A21))*Допущения!C33/360-(($B$12*$A21))*Допущения!C33/360)))/(1+F$18)^3+(((($B$9+($A21-1)*$B$14))*(1-Допущения!C37)+Модель!AB16-((($B$14*$A21))*Допущения!C33/360-(($B$13*$A21))*Допущения!C33/360)))/(1+F$18)^4+(((($B$10+($A21-1)*$B$15))*(1-Допущения!C37)+Модель!AC16-((($B$15*$A21))*Допущения!C33/360-(($B$14*$A21))*Допущения!C33/360)))/(1+F$18)^5-(Допущения!C18)/(1+F$18)^3+((($B$10+($A21-1)*$B$15)*(1-Допущения!C37)+Модель!AC16)/(1+F$18)^6+(($B$10+($A21-1)*$B$15)*(1-Допущения!C37)+Модель!AC16)/(1+F$18)^7) -> 39931801
A22: 1.1 | B22: =-Допущения!C16+(((($B$6+($A22-1)*$B$11))*(1-Допущения!C37)+SUM(Модель!C16:N16)-((($B$11*$A22))*Допущения!C33/360-(0)*Допущения!C33/360)))/(1+B$18)^1+(((($B$7+($A22-1)*$B$12))*(1-Допущения!C37)+SUM(Модель!O16:Z16)-((($B$12*$A22))*Допущения!C33/360-(($B$11*$A22))*Допущения!C33/360)))/(1+B$18)^2+(((($B$8+($A22-1)*$B$13))*(1-Допущения!C37)+Модель!AA16-((($B$13*$A22))*Допущения!C33/360-(($B$12*$A22))*Допущения!C33/360)))/(1+B$18)^3+(((($B$9+($A22-1)*$B$14))*(1-Допущения!C37)+Модель!AB16-((($B$14*$A22))*Допущения!C33/360-(($B$13*$A22))*Допущения!C33/360)))/(1+B$18)^4+(((($B$10+($A22-1)*$B$15))*(1-Допущения!C37)+Модель!AC16-((($B$15*$A22))*Допущения!C33/360-(($B$14*$A22))*Допущения!C33/360)))/(1+B$18)^5-(Допущения!C18)/(1+B$18)^3+((($B$10+($A22-1)*$B$15)*(1-Допущения!C37)+Модель!AC16)/(1+B$18)^6+(($B$10+($A22-1)*$B$15)*(1-Допущения!C37)+Модель!AC16)/(1+B$18)^7) -> 1.7966374e+08 | C22: =-Допущения!C16+(((($B$6+($A22-1)*$B$11))*(1-Допущения!C37)+SUM(Модель!C16:N16)-((($B$11*$A22))*Допущения!C33/360-(0)*Допущения!C33/360)))/(1+C$18)^1+(((($B$7+($A22-1)*$B$12))*(1-Допущения!C37)+SUM(Модель!O16:Z16)-((($B$12*$A22))*Допущения!C33/360-(($B$11*$A22))*Допущения!C33/360)))/(1+C$18)^2+(((($B$8+($A22-1)*$B$13))*(1-Допущения!C37)+Модель!AA16-((($B$13*$A22))*Допущения!C33/360-(($B$12*$A22))*Допущения!C33/360)))/(1+C$18)^3+(((($B$9+($A22-1)*$B$14))*(1-Допущения!C37)+Модель!AB16-((($B$14*$A22))*Допущения!C33/360-(($B$13*$A22))*Допущения!C33/360)))/(1+C$18)^4+(((($B$10+($A22-1)*$B$15))*(1-Допущения!C37)+Модель!AC16-((($B$15*$A22))*Допущения!C33/360-(($B$14*$A22))*Допущения!C33/360)))/(1+C$18)^5-(Допущения!C18)/(1+C$18)^3+((($B$10+($A22-1)*$B$15)*(1-Допущения!C37)+Модель!AC16)/(1+C$18)^6+(($B$10+($A22-1)*$B$15)*(1-Допущения!C37)+Модель!AC16)/(1+C$18)^7) -> 1.5325534e+08 | D22: =-Допущения!C16+(((($B$6+($A22-1)*$B$11))*(1-Допущения!C37)+SUM(Модель!C16:N16)-((($B$11*$A22))*Допущения!C33/360-(0)*Допущения!C33/360)))/(1+D$18)^1+(((($B$7+($A22-1)*$B$12))*(1-Допущения!C37)+SUM(Модель!O16:Z16)-((($B$12*$A22))*Допущения!C33/360-(($B$11*$A22))*Допущения!C33/360)))/(1+D$18)^2+(((($B$8+($A22-1)*$B$13))*(1-Допущения!C37)+Модель!AA16-((($B$13*$A22))*Допущения!C33/360-(($B$12*$A22))*Допущения!C33/360)))/(1+D$18)^3+(((($B$9+($A22-1)*$B$14))*(1-Допущения!C37)+Модель!AB16-((($B$14*$A22))*Допущения!C33/360-(($B$13*$A22))*Допущения!C33/360)))/(1+D$18)^4+(((($B$10+($A22-1)*$B$15))*(1-Допущения!C37)+Модель!AC16-((($B$15*$A22))*Допущения!C33/360-(($B$14*$A22))*Допущения!C33/360)))/(1+D$18)^5-(Допущения!C18)/(1+D$18)^3+((($B$10+($A22-1)*$B$15)*(1-Допущения!C37)+Модель!AC16)/(1+D$18)^6+(($B$10+($A22-1)*$B$15)*(1-Допущения!C37)+Модель!AC16)/(1+D$18)^7) -> 1.3786557e+08 | E22: =-Допущения!C16+(((($B$6+($A22-1)*$B$11))*(1-Допущения!C37)+SUM(Модель!C16:N16)-((($B$11*$A22))*Допущения!C33/360-(0)*Допущения!C33/360)))/(1+E$18)^1+(((($B$7+($A22-1)*$B$12))*(1-Допущения!C37)+SUM(Модель!O16:Z16)-((($B$12*$A22))*Допущения!C33/360-(($B$11*$A22))*Допущения!C33/360)))/(1+E$18)^2+(((($B$8+($A22-1)*$B$13))*(1-Допущения!C37)+Модель!AA16-((($B$13*$A22))*Допущения!C33/360-(($B$12*$A22))*Допущения!C33/360)))/(1+E$18)^3+(((($B$9+($A22-1)*$B$14))*(1-Допущения!C37)+Модель!AB16-((($B$14*$A22))*Допущения!C33/360-(($B$13*$A22))*Допущения!C33/360)))/(1+E$18)^4+(((($B$10+($A22-1)*$B$15))*(1-Допущения!C37)+Модель!AC16-((($B$15*$A22))*Допущения!C33/360-(($B$14*$A22))*Допущения!C33/360)))/(1+E$18)^5-(Допущения!C18)/(1+E$18)^3+((($B$10+($A22-1)*$B$15)*(1-Допущения!C37)+Модель!AC16)/(1+E$18)^6+(($B$10+($A22-1)*$B$15)*(1-Допущения!C37)+Модель!AC16)/(1+E$18)^7) -> 1.2400207e+08 | F22: =-Допущения!C16+(((($B$6+($A22-1)*$B$11))*(1-Допущения!C37)+SUM(Модель!C16:N16)-((($B$11*$A22))*Допущения!C33/360-(0)*Допущения!C33/360)))/(1+F$18)^1+(((($B$7+($A22-1)*$B$12))*(1-Допущения!C37)+SUM(Модель!O16:Z16)-((($B$12*$A22))*Допущения!C33/360-(($B$11*$A22))*Допущения!C33/360)))/(1+F$18)^2+(((($B$8+($A22-1)*$B$13))*(1-Допущения!C37)+Модель!AA16-((($B$13*$A22))*Допущения!C33/360-(($B$12*$A22))*Допущения!C33/360)))/(1+F$18)^3+(((($B$9+($A22-1)*$B$14))*(1-Допущения!C37)+Модель!AB16-((($B$14*$A22))*Допущения!C33/360-(($B$13*$A22))*Допущения!C33/360)))/(1+F$18)^4+(((($B$10+($A22-1)*$B$15))*(1-Допущения!C37)+Модель!AC16-((($B$15*$A22))*Допущения!C33/360-(($B$14*$A22))*Допущения!C33/360)))/(1+F$18)^5-(Допущения!C18)/(1+F$18)^3+((($B$10+($A22-1)*$B$15)*(1-Допущения!C37)+Модель!AC16)/(1+F$18)^6+(($B$10+($A22-1)*$B$15)*(1-Допущения!C37)+Модель!AC16)/(1+F$18)^7) -> 1.0568382e+08
A23: 1.2 | B23: =-Допущения!C16+(((($B$6+($A23-1)*$B$11))*(1-Допущения!C37)+SUM(Модель!C16:N16)-((($B$11*$A23))*Допущения!C33/360-(0)*Допущения!C33/360)))/(1+B$18)^1+(((($B$7+($A23-1)*$B$12))*(1-Допущения!C37)+SUM(Модель!O16:Z16)-((($B$12*$A23))*Допущения!C33/360-(($B$11*$A23))*Допущения!C33/360)))/(1+B$18)^2+(((($B$8+($A23-1)*$B$13))*(1-Допущения!C37)+Модель!AA16-((($B$13*$A23))*Допущения!C33/360-(($B$12*$A23))*Допущения!C33/360)))/(1+B$18)^3+(((($B$9+($A23-1)*$B$14))*(1-Допущения!C37)+Модель!AB16-((($B$14*$A23))*Допущения!C33/360-(($B$13*$A23))*Допущения!C33/360)))/(1+B$18)^4+(((($B$10+($A23-1)*$B$15))*(1-Допущения!C37)+Модель!AC16-((($B$15*$A23))*Допущения!C33/360-(($B$14*$A23))*Допущения!C33/360)))/(1+B$18)^5-(Допущения!C18)/(1+B$18)^3+((($B$10+($A23-1)*$B$15)*(1-Допущения!C37)+Модель!AC16)/(1+B$18)^6+(($B$10+($A23-1)*$B$15)*(1-Допущения!C37)+Модель!AC16)/(1+B$18)^7) -> 2.7163235e+08 | C23: =-Допущения!C16+(((($B$6+($A23-1)*$B$11))*(1-Допущения!C37)+SUM(Модель!C16:N16)-((($B$11*$A23))*Допущения!C33/360-(0)*Допущения!C33/360)))/(1+C$18)^1+(((($B$7+($A23-1)*$B$12))*(1-Допущения!C37)+SUM(Модель!O16:Z16)-((($B$12*$A23))*Допущения!C33/360-(($B$11*$A23))*Допущения!C33/360)))/(1+C$18)^2+(((($B$8+($A23-1)*$B$13))*(1-Допущения!C37)+Модель!AA16-((($B$13*$A23))*Допущения!C33/360-(($B$12*$A23))*Допущения!C33/360)))/(1+C$18)^3+(((($B$9+($A23-1)*$B$14))*(1-Допущения!C37)+Модель!AB16-((($B$14*$A23))*Допущения!C33/360-(($B$13*$A23))*Допущения!C33/360)))/(1+C$18)^4+(((($B$10+($A23-1)*$B$15))*(1-Допущения!C37)+Модель!AC16-((($B$15*$A23))*Допущения!C33/360-(($B$14*$A23))*Допущения!C33/360)))/(1+C$18)^5-(Допущения!C18)/(1+C$18)^3+((($B$10+($A23-1)*$B$15)*(1-Допущения!C37)+Модель!AC16)/(1+C$18)^6+(($B$10+($A23-1)*$B$15)*(1-Допущения!C37)+Модель!AC16)/(1+C$18)^7) -> 2.3597651e+08 | D23: =-Допущения!C16+(((($B$6+($A23-1)*$B$11))*(1-Допущения!C37)+SUM(Модель!C16:N16)-((($B$11*$A23))*Допущения!C33/360-(0)*Допущения!C33/360)))/(1+D$18)^1+(((($B$7+($A23-1)*$B$12))*(1-Допущения!C37)+SUM(Модель!O16:Z16)-((($B$12*$A23))*Допущения!C33/360-(($B$11*$A23))*Допущения!C33/360)))/(1+D$18)^2+(((($B$8+($A23-1)*$B$13))*(1-Допущения!C37)+Модель!AA16-((($B$13*$A23))*Допущения!C33/360-(($B$12*$A23))*Допущения!C33/360)))/(1+D$18)^3+(((($B$9+($A23-1)*$B$14))*(1-Допущения!C37)+Модель!AB16-((($B$14*$A23))*Допущения!C33/360-(($B$13*$A23))*Допущения!C33/360)))/(1+D$18)^4+(((($B$10+($A23-1)*$B$15))*(1-Допущения!C37)+Модель!AC16-((($B$15*$A23))*Допущения!C33/360-(($B$14*$A23))*Допущения!C33/360)))/(1+D$18)^5-(Допущения!C18)/(1+D$18)^3+((($B$10+($A23-1)*$B$15)*(1-Допущения!C37)+Модель!AC16)/(1+D$18)^6+(($B$10+($A23-1)*$B$15)*(1-Допущения!C37)+Модель!AC16)/(1+D$18)^7) -> 2.1514605e+08 | E23: =-Допущения!C16+(((($B$6+($A23-1)*$B$11))*(1-Допущения!C37)+SUM(Модель!C16:N16)-((($B$11*$A23))*Допущения!C33/360-(0)*Допущения!C33/360)))/(1+E$18)^1+(((($B$7+($A23-1)*$B$12))*(1-Допущения!C37)+SUM(Модель!O16:Z16)-((($B$12*$A23))*Допущения!C33/360-(($B$11*$A23))*Допущения!C33/360)))/(1+E$18)^2+(((($B$8+($A23-1)*$B$13))*(1-Допущения!C37)+Модель!AA16-((($B$13*$A23))*Допущения!C33/360-(($B$12*$A23))*Допущения!C33/360)))/(1+E$18)^3+(((($B$9+($A23-1)*$B$14))*(1-Допущения!C37)+Модель!AB16-((($B$14*$A23))*Допущения!C33/360-(($B$13*$A23))*Допущения!C33/360)))/(1+E$18)^4+(((($B$10+($A23-1)*$B$15))*(1-Допущения!C37)+Модель!AC16-((($B$15*$A23))*Допущения!C33/360-(($B$14*$A23))*Допущения!C33/360)))/(1+E$18)^5-(Допущения!C18)/(1+E$18)^3+((($B$10+($A23-1)*$B$15)*(1-Допущения!C37)+Модель!AC16)/(1+E$18)^6+(($B$10+($A23-1)*$B$15)*(1-Допущения!C37)+Модель!AC16)/(1+E$18)^7) -> 1.963436e+08 | F23: =-Допущения!C16+(((($B$6+($A23-1)*$B$11))*(1-Допущения!C37)+SUM(Модель!C16:N16)-((($B$11*$A23))*Допущения!C33/360-(0)*Допущения!C33/360)))/(1+F$18)^1+(((($B$7+($A23-1)*$B$12))*(1-Допущения!C37)+SUM(Модель!O16:Z16)-((($B$12*$A23))*Допущения!C33/360-(($B$11*$A23))*Допущения!C33/360)))/(1+F$18)^2+(((($B$8+($A23-1)*$B$13))*(1-Допущения!C37)+Модель!AA16-((($B$13*$A23))*Допущения!C33/360-(($B$12*$A23))*Допущения!C33/360)))/(1+F$18)^3+(((($B$9+($A23-1)*$B$14))*(1-Допущения!C37)+Модель!AB16-((($B$14*$A23))*Допущения!C33/360-(($B$13*$A23))*Допущения!C33/360)))/(1+F$18)^4+(((($B$10+($A23-1)*$B$15))*(1-Допущения!C37)+Модель!AC16-((($B$15*$A23))*Допущения!C33/360-(($B$14*$A23))*Допущения!C33/360)))/(1+F$18)^5-(Допущения!C18)/(1+F$18)^3+((($B$10+($A23-1)*$B$15)*(1-Допущения!C37)+Модель!AC16)/(1+F$18)^6+(($B$10+($A23-1)*$B$15)*(1-Допущения!C37)+Модель!AC16)/(1+F$18)^7) -> 1.7143584e+08
